[
    {
        "nombre":"6th SYMPOSIUM: International Language Day - 2023 'New Trends in Didactic and Pedagogical Approaches in Foreign Language Teaching'",
        "fecha": "27 de abril de 2023",
        "hora": "08:30 am a 12:00 pm",
        "transmision":"https://www.youtube.com/user/universidadunad",
        "inscripcion": "https://docs.google.com/forms/d/e/1FAIpQLSfXqbL-t8_fE81uSuhM4tQDRAntfAa0q8nheVdL7uRnvybOaA/viewform"
    },
    {
        "nombre":"Hablemos de biotecnología, un mundo de grandes oportunidades: Tendencias en Biotecnología alimentaria",
        "fecha": "27 de abril de 2023",
        "hora": "09:30 am",
        "transmision":"https://www.youtube.com/user/universidadunad",
        "inscripcion": "https://forms.gle/1bX8we9bhUZmK33p6"
    }
]
